qcSubroutines/__init__.py
qcSubroutines/subroutines.py
qcSubroutines-0.1.4.dist-info/LICENCE.txt
qcSubroutines-0.1.4.dist-info/METADATA
qcSubroutines-0.1.4.dist-info/WHEEL
qcSubroutines-0.1.4.dist-info/top_level.txt
qcSubroutines-0.1.4.dist-info/RECORD
